{
  "id": "hero",
  "type": "SharedSlice",
  "name": "Hero",
  "description": "Hero",
  "variations": [
    {
      "id": "default",
      "name": "Default",
      "docURL": "...",
      "version": "initial",
      "description": "Default",
      "imageUrl": "",
      "primary": {
        "title": {
          "type": "StructuredText",
          "config": {
            "label": "Title",
            "placeholder": "",
            "allowTargetBlank": true,
            "multi": "paragraph,preformatted,heading2,heading3,heading4,heading5,heading6,strong,em,hyperlink,image,embed,list-item,o-list-item,rtl"
          }
        },
        "subtitle": {
          "type": "StructuredText",
          "config": {
            "label": "Subtitle",
            "placeholder": "",
            "allowTargetBlank": true,
            "multi": "preformatted,heading1,heading2,heading3,heading4,heading5,heading6,strong,em,hyperlink,image,embed,list-item,o-list-item,rtl"
          }
        },
        "hero_image": {
          "type": "Image",
          "config": {
            "label": "Hero Image",
            "constraint": {},
            "thumbnails": []
          }
        },
        "buttons": {
          "type": "Group",
          "config": {
            "label": "Buttons",
            "repeat": true,
            "fields": {
              "button_text": {
                "type": "Text",
                "config": {
                  "label": "Button Text",
                  "placeholder": ""
                }
              },
              "button_link": {
                "type": "Link",
                "config": {
                  "label": " Button Link",
                  "placeholder": "",
                  "select": null,
                  "allowTargetBlank": true,
                  "allowText": true,
                  "repeat": false
                }
              },
              "button_type": {
                "type": "Select",
                "config": {
                  "label": " Button Type",
                  "placeholder": "",
                  "options": [
                    "primary",
                    "secondary"
                  ]
                }
              }
            }
          }
        },
        "stats": {
          "type": "Group",
          "config": {
            "label": "stats",
            "repeat": true,
            "fields": {
              "number": {
                "type": "Number",
                "config": {
                  "label": "Number",
                  "placeholder": ""
                }
              },
              "label": {
                "type": "Text",
                "config": {
                  "label": "Label",
                  "placeholder": ""
                }
              }
            }
          }
        }
      },
      "items": {}
    }
  ]
}